easy_vault/__init__.py
easy_vault/_easy_vault.py
easy_vault/_keyring.py
easy_vault/_password.py
easy_vault/_version.py
easy_vault/cli/__init__.py
easy_vault/cli/_common_options.py
easy_vault/cli/cli.py
easy_vault-0.7.0.dist-info/LICENSE
easy_vault-0.7.0.dist-info/METADATA
easy_vault-0.7.0.dist-info/WHEEL
easy_vault-0.7.0.dist-info/entry_points.txt
easy_vault-0.7.0.dist-info/top_level.txt
easy_vault-0.7.0.dist-info/zip-safe
easy_vault-0.7.0.dist-info/RECORD
