Metadata-Version: 2.1
Name: easy-vault
Version: 0.7.0
Summary: Secure vault files that are easy to use
Home-page: https://github.com/andy-maier/easy-vault
Author: Andreas Maier
Author-email: andreas.r.maier@gmx.de
Maintainer: Andreas Maier
Maintainer-email: andreas.r.maier@gmx.de
License: Apache Software License 2.0
Project-URL: Bug Tracker, https://github.com/andy-maier/easy-vault/issues
Project-URL: Documentation, https://easy-vault.readthedocs.io/en/stable/
Project-URL: Change Log, https://easy-vault.readthedocs.io/en/stable/changes.html
Platform: any
Classifier: Development Status :: 4 - Beta
Classifier: Environment :: Console
Classifier: Intended Audience :: Developers
Classifier: License :: OSI Approved :: Apache Software License
Classifier: Operating System :: OS Independent
Classifier: Programming Language :: Python :: 2
Classifier: Programming Language :: Python :: 2.7
Classifier: Programming Language :: Python :: 3
Classifier: Programming Language :: Python :: 3.4
Classifier: Programming Language :: Python :: 3.5
Classifier: Programming Language :: Python :: 3.6
Classifier: Programming Language :: Python :: 3.7
Classifier: Programming Language :: Python :: 3.8
Classifier: Programming Language :: Python :: 3.9
Classifier: Topic :: Software Development :: Libraries :: Python Modules
Requires-Python: >=2.7, !=3.0.*, !=3.1.*, !=3.2.*, !=3.3.*
Requires-Dist: six (>=1.14.0)
Requires-Dist: yamlloader (>=0.5.5)
Requires-Dist: cffi (>=1.14.5)
Requires-Dist: cryptography (<3.4,>=3.3) ; python_version == "2.7"
Requires-Dist: keyring (<19.0.0,>=18.0.0) ; python_version == "2.7"
Requires-Dist: PyYAML (>=5.3.1) ; python_version == "2.7"
Requires-Dist: Click (>=7.1.1) ; python_version == "2.7"
Requires-Dist: configparser (<5.0,>=3.5) ; python_version == "2.7"
Requires-Dist: cryptography (<2.9,>=2.8) ; python_version == "3.4"
Requires-Dist: keyring (<19.0.0,>=18.0.0) ; python_version == "3.4"
Requires-Dist: PyYAML (<5.3,>=5.2) ; python_version == "3.4"
Requires-Dist: Click (<7.1,>=7.0) ; python_version == "3.4"
Requires-Dist: cryptography (<3.3,>=3.2.1) ; python_version == "3.5"
Requires-Dist: keyring (<21.0.0,>=18.0.0) ; python_version == "3.5"
Requires-Dist: PyYAML (>=5.3.1) ; python_version > "3.4"
Requires-Dist: Click (>=7.1.1) ; python_version >= "3.5"
Requires-Dist: cryptography (>=3.4.7) ; python_version >= "3.6"
Requires-Dist: keyring (>=18.0.0) ; python_version >= "3.6"
Requires-Dist: pywin32-ctypes (>=0.2.0) ; sys_platform == "win32"
